lmsimple/__init__.py
lmsimple/backend.py
lmsimple/constants.py
lmsimple/core.py
lmsimple/models.py
lmsimple-1.0.dist-info/METADATA
lmsimple-1.0.dist-info/WHEEL
lmsimple-1.0.dist-info/entry_points.txt
lmsimple-1.0.dist-info/licenses/LICENSE
lmsimple-1.0.dist-info/RECORD
